{
    "client": "Thunder Client",
    "collectionName": "gin_mongodb",
    "dateExported": "2022-09-24T05:47:35.140Z",
    "version": "1.1",
    "folders": [],
    "requests": [
        {
            "_id": "d115f66a-12e1-4437-90f0-73b0540f5b9c",
            "colId": "75fbf0ab-db3e-44ce-a96f-867108c9c9da",
            "containerId": "",
            "name": "add_todo",
            "url": "http://localhost:3000/todos",
            "method": "POST",
            "sortNum": 10000,
            "created": "2022-09-24T01:02:22.810Z",
            "modified": "2022-09-24T01:43:12.660Z",
            "headers": [],
            "params": [],
            "body": {
                "type": "json",
                "raw": "{\n  \"Title\": \"Đọc sách\",\n  \"Des\": \"Đây là công việc số 1\",\n  \"Completed\": true\n}",
                "form": []
            },
            "tests": []
        },
        {
            "_id": "4aa4c0c8-63b2-4b41-800c-1e68c985b097",
            "colId": "75fbf0ab-db3e-44ce-a96f-867108c9c9da",
            "containerId": "",
            "name": "get_todos",
            "url": "http://localhost:3000/todos",
            "method": "GET",
            "sortNum": 20000,
            "created": "2022-09-24T01:45:07.230Z",
            "modified": "2022-09-24T01:45:14.742Z",
            "headers": [],
            "params": [],
            "tests": []
        },
        {
            "_id": "50e2c788-a9a9-4e46-9e9f-4326f3d2a510",
            "colId": "75fbf0ab-db3e-44ce-a96f-867108c9c9da",
            "containerId": "",
            "name": "get_todo_by_id",
            "url": "http://localhost:3000/todos/632e60b0bb9cdde031a8de08",
            "method": "GET",
            "sortNum": 30000,
            "created": "2022-09-24T01:57:16.993Z",
            "modified": "2022-09-24T02:22:10.849Z",
            "headers": [],
            "params": [],
            "tests": []
        },
        {
            "_id": "13314daa-c31a-4f0e-89a1-a080a0f430b8",
            "colId": "75fbf0ab-db3e-44ce-a96f-867108c9c9da",
            "containerId": "",
            "name": "delete_todo_by_id",
            "url": "http://localhost:3000/todos/632e60b0bb9cdde031a8de08",
            "method": "DELETE",
            "sortNum": 40000,
            "created": "2022-09-24T02:30:13.476Z",
            "modified": "2022-09-24T04:04:55.092Z",
            "headers": [],
            "params": [],
            "tests": []
        },
        {
            "_id": "4ed960a0-270c-4137-8614-8d567342da70",
            "colId": "75fbf0ab-db3e-44ce-a96f-867108c9c9da",
            "containerId": "",
            "name": "update_todo_by_id",
            "url": "http://localhost:3000/todos/632e85d9faedf00df1c05751",
            "method": "PUT",
            "sortNum": 50000,
            "created": "2022-09-24T04:01:21.924Z",
            "modified": "2022-09-24T04:44:57.546Z",
            "headers": [],
            "params": [],
            "body": {
                "type": "json",
                "raw": "{\n  \"Title\": \"Đọc sách update\",\n  \"Des\": \"Đây là công việc số 1 update\",\n  \"Completed\": false\n}",
                "form": []
            },
            "tests": []
        }
    ]
}
